pyphg/README.md
pyphg/__init__.py
pyphg/__main__.py
pyphg/_pyphg.cpython-310-x86_64-linux-gnu.so
pyphg/_pyphg.cpython-311-x86_64-linux-gnu.so
pyphg/_pyphg.cpython-312-x86_64-linux-gnu.so
pyphg/_pyphg.cpython-38-x86_64-linux-gnu.so
pyphg/_pyphg.cpython-39-x86_64-linux-gnu.so
pyphg/examples/simplest.py
pyphg/lib/libphg.so
pyphg-0.9.10.dist-info/METADATA
pyphg-0.9.10.dist-info/WHEEL
pyphg-0.9.10.dist-info/top_level.txt
pyphg-0.9.10.dist-info/RECORD
