Metadata-Version: 2.1
Name: pyphg
Version: 0.9.10
Summary: Parallel Hierarchy Grid
Author: MSCAX
License: LGPL
Classifier: Programming Language :: Python :: 3.8
Classifier: Intended Audience :: Science/Research
Classifier: Operating System :: OS Independent
Classifier: Development Status :: 4 - Beta
Classifier: Topic :: Scientific/Engineering :: Artificial Intelligence
Requires-Python: >=3.8
